setup.py
mlnd_GBP_distribution/Binomialdistribution.py
mlnd_GBP_distribution/Gaussiandistribution.py
mlnd_GBP_distribution/Generaldistribution.py
mlnd_GBP_distribution/__init__.py
mlnd_GBP_distribution.egg-info/PKG-INFO
mlnd_GBP_distribution.egg-info/SOURCES.txt
mlnd_GBP_distribution.egg-info/dependency_links.txt
mlnd_GBP_distribution.egg-info/not-zip-safe
mlnd_GBP_distribution.egg-info/top_level.txt