Metadata-Version: 1.0
Name: mlnd-GBP-distribution
Version: 0.1
Summary: Gaussian and Binomial distributions
Home-page: UNKNOWN
Author: Supuli Jayaweera
Author-email: UNKNOWN
License: UNKNOWN
Platform: UNKNOWN
